jupyterlab_notifications/__init__.py
jupyterlab_notifications/_version.py
jupyterlab_notifications-0.5.0.data/data/share/jupyter/labextensions/jupyterlab-notifications/package.json
jupyterlab_notifications-0.5.0.data/data/share/jupyter/labextensions/jupyterlab-notifications/schemas/jupyterlab-notifications/package.json.orig
jupyterlab_notifications-0.5.0.data/data/share/jupyter/labextensions/jupyterlab-notifications/schemas/jupyterlab-notifications/plugin.json
jupyterlab_notifications-0.5.0.data/data/share/jupyter/labextensions/jupyterlab-notifications/static/223.cc403c9c3f814d717d55.js
jupyterlab_notifications-0.5.0.data/data/share/jupyter/labextensions/jupyterlab-notifications/static/593.a3fdc55f17e0a05733ff.js
jupyterlab_notifications-0.5.0.data/data/share/jupyter/labextensions/jupyterlab-notifications/static/700.2068b5b2716fcc63a4fa.js
jupyterlab_notifications-0.5.0.data/data/share/jupyter/labextensions/jupyterlab-notifications/static/747.ee576baefaf09ce956a1.js
jupyterlab_notifications-0.5.0.data/data/share/jupyter/labextensions/jupyterlab-notifications/static/762.ca2e7bce676a705fe19c.js
jupyterlab_notifications-0.5.0.data/data/share/jupyter/labextensions/jupyterlab-notifications/static/762.ca2e7bce676a705fe19c.js.LICENSE.txt
jupyterlab_notifications-0.5.0.data/data/share/jupyter/labextensions/jupyterlab-notifications/static/remoteEntry.d7c47c0b5faf71e6f9a8.js
jupyterlab_notifications-0.5.0.data/data/share/jupyter/labextensions/jupyterlab-notifications/static/style.js
jupyterlab_notifications-0.5.0.data/data/share/jupyter/labextensions/jupyterlab-notifications/static/third-party-licenses.json
jupyterlab_notifications-0.5.0.data/data/share/jupyter/labextensions/jupyterlab-notifications/install.json
jupyterlab_notifications-0.5.0.dist-info/METADATA
jupyterlab_notifications-0.5.0.dist-info/WHEEL
jupyterlab_notifications-0.5.0.dist-info/licenses/LICENSE
jupyterlab_notifications-0.5.0.dist-info/RECORD
