Metadata-Version: 2.1
Name: jupyterlab-notifications
Version: 0.5.0
Summary: Jupyterlab extension to show notebook cell completion browser notifications
Project-URL: Homepage, https://github.com/mwakaba2/jupyterlab-notifications
Project-URL: Bug Tracker, https://github.com/mwakaba2/jupyterlab-notifications/issues
Project-URL: Repository, https://github.com/mwakaba2/jupyterlab-notifications.git
Author: Mariko Wakabayashi
License: BSD 3-Clause License
License-File: LICENSE
Classifier: Framework :: Jupyter
Classifier: Framework :: Jupyter :: JupyterLab
Classifier: Framework :: Jupyter :: JupyterLab :: 4
Classifier: Framework :: Jupyter :: JupyterLab :: Extensions
Classifier: Framework :: Jupyter :: JupyterLab :: Extensions :: Prebuilt
Classifier: License :: OSI Approved :: BSD License
Classifier: Programming Language :: Python
Classifier: Programming Language :: Python :: 3
Classifier: Programming Language :: Python :: 3.8
Classifier: Programming Language :: Python :: 3.9
Classifier: Programming Language :: Python :: 3.10
Classifier: Programming Language :: Python :: 3.11
Requires-Python: >=3.8
